kriya/__init__.py
kriya-0.0.1.dist-info/LICENSE
kriya-0.0.1.dist-info/METADATA
kriya-0.0.1.dist-info/WHEEL
kriya-0.0.1.dist-info/RECORD
